<annotation>
	<folder>RegistrationCard</folder>
	<filename>0AwEi151901.jpg</filename>
	<path>C:\Users\asyra\Documents\notebooks\text recognition in image\image\RegistrationCard\0AwEi151901.jpg</path>
	<source>
		<database>Unknown</database>
	</source>
	<size>
		<width>2745</width>
		<height>3909</height>
		<depth>3</depth>
	</size>
	<segmented>0</segmented>
	<object>
		<name>rc</name>
		<pose>Unspecified</pose>
		<truncated>0</truncated>
		<difficult>0</difficult>
		<bndbox>
			<xmin>40</xmin>
			<ymin>265</ymin>
			<xmax>1493</xmax>
			<ymax>1965</ymax>
		</bndbox>
	</object>
</annotation>
